{
  "core": {
    "services": [
      "LocationService",
      "LocalStorageService",
      "BaseHttpService"
    ],
    "models": ["LocationModel"]
  },
  "authentication": {
    "services": ["AuthenticationService"],
    "models": ["AuthenticationModel"],
    "guards": ["AuthenticationGuard"]
  },
  "modules": {
    "search": {
      "components": ["SearchBarComponent", "SearchFiltersComponent", "SearchResultsComponent"],
      "services": ["SearchService"],
      "models": ["SearchModel"]
    },
    "categories": {
      "components": ["SelectCategoriesComponent"],
      "services": ["CategoriesService"],
      "models": ["CategoryModel"]
    },
    "user": {
      "components": ["UserComponent"],
      "services": ["UserService"],
      "models": ["UserModel"]
    }
  },
  "shared": {
    "layout": {
      "nav": ["NavbarComponent"],
      "footer": ["FooterComponent"]
    }
  }
}